MANIFEST.in
README.txt
bootstrap.py
setup.cfg
setup.py
test-plone-4.1.x.cfg
collective/__init__.py
collective.behavior.contactinfo.egg-info/PKG-INFO
collective.behavior.contactinfo.egg-info/SOURCES.txt
collective.behavior.contactinfo.egg-info/dependency_links.txt
collective.behavior.contactinfo.egg-info/entry_points.txt
collective.behavior.contactinfo.egg-info/namespace_packages.txt
collective.behavior.contactinfo.egg-info/not-zip-safe
collective.behavior.contactinfo.egg-info/requires.txt
collective.behavior.contactinfo.egg-info/top_level.txt
collective/behavior/__init__.py
collective/behavior/contactinfo/README.txt
collective/behavior/contactinfo/__init__.py
collective/behavior/contactinfo/config.py
collective/behavior/contactinfo/configure.zcml
collective/behavior/contactinfo/testing.py
collective/behavior/contactinfo/utils.py
collective/behavior/contactinfo/version.txt
collective/behavior/contactinfo/vocabulary.py
collective/behavior/contactinfo/behavior/__init__.py
collective/behavior/contactinfo/behavior/address.py
collective/behavior/contactinfo/behavior/configure.zcml
collective/behavior/contactinfo/behavior/contactinfo.py
collective/behavior/contactinfo/docs/__init__.py
collective/behavior/contactinfo/docs/address.txt
collective/behavior/contactinfo/docs/netcontactinfo.txt
collective/behavior/contactinfo/docs/phonecontactinfo.txt
collective/behavior/contactinfo/interfaces/__init__.py
collective/behavior/contactinfo/locales/collective.behavior.contactinfo.pot
collective/behavior/contactinfo/locales/generateMo.sh
collective/behavior/contactinfo/locales/manual.pot
collective/behavior/contactinfo/locales/rebuildAll.sh
collective/behavior/contactinfo/locales/en/LC_MESSAGES/collective.behavior.contactinfo.po
collective/behavior/contactinfo/locales/es/LC_MESSAGES/collective.behavior.contactinfo.po
collective/behavior/contactinfo/locales/pt_BR/LC_MESSAGES/collective.behavior.contactinfo.po
collective/behavior/contactinfo/tests/__init__.py
collective/behavior/contactinfo/tests/test_address.py
collective/behavior/contactinfo/tests/test_doctest.py
collective/behavior/contactinfo/tests/test_netinfo.py
collective/behavior/contactinfo/tests/test_phoneinfo.py
docs/HISTORY.txt
docs/INSTALL.txt
docs/LICENSE.GPL
docs/LICENSE.txt