Metadata-Version: 1.0
Name: collective.behavior.contactinfo
Version: 0.9
Summary: A set of dexterity behaviors providing common contact info fields
Home-page: http://www.simplesconsultoria.com.br/
Author: Simples Consultoria
Author-email: products@simplesconsultoria.com.br
License: GPL
Keywords: dexterity behavior plone
Platform: UNKNOWN
Classifier: Framework :: Plone
Classifier: Framework :: Zope2
Classifier: Framework :: Zope3
Classifier: Programming Language :: Python
Classifier: Topic :: Software Development :: Libraries :: Python Modules
